{
  "$schema": "https://json-schema.org/draft/2020-12/schema",
  "$id": "https://example.org/ggplot3scene/scene3d.schema.json",
  "title": "Scene3D v0.1",
  "type": "object",
  "required": ["schemaVersion", "sceneId", "coordinateSystem", "layers", "camera", "axes", "theme", "metadata"],
  "properties": {
    "schemaVersion": { "const": "0.1.0" },
    "sceneId": { "type": "string" },
    "coordinateSystem": {
      "type": "object",
      "required": ["type", "handedness", "origin", "originMode", "domain", "aspect"],
      "properties": {
        "type": { "const": "cartesian3d" },
        "handedness": { "const": "right" },
        "origin": { "$ref": "#/$defs/vec3" },
        "originMode": { "enum": ["fixed", "data_min", "data_center"] },
        "domain": { "$ref": "#/$defs/domain3" },
        "aspect": { "type": "object" }
      }
    },
    "layers": {
      "type": "array",
      "items": {
        "oneOf": [
          { "$ref": "#/$defs/pointCloudLayer" },
          { "$ref": "#/$defs/surfaceGridLayer" },
          { "$ref": "#/$defs/absAnnotationLayer" }
        ]
      }
    },
    "camera": {
      "type": "object",
      "required": ["projection", "position", "target", "up", "zoom"],
      "properties": {
        "projection": { "enum": ["orthographic", "perspective"] },
        "position": { "$ref": "#/$defs/vec3" },
        "target": { "$ref": "#/$defs/vec3" },
        "up": { "$ref": "#/$defs/vec3" },
        "zoom": { "type": "number", "exclusiveMinimum": 0 }
      }
    },
    "axes": {
      "type": "object",
      "properties": {
        "grid": {
          "type": "object",
          "properties": {
            "visible": { "type": "boolean" },
            "planes": {
              "type": "array",
              "items": { "enum": ["xy", "xz", "yz"] }
            },
            "domainMode": { "enum": ["full", "positive", "negative", "limits"] },
            "origin": { "$ref": "#/$defs/vec3" },
            "domain": { "$ref": "#/$defs/domain3" },
            "majorBreaks": { "type": "object" }
          }
        }
      }
    },
    "lights": { "type": "object" },
    "theme": { "type": "object" },
    "metadata": { "type": "object" }
  },
  "$defs": {
    "vec3": {
      "type": "array",
      "prefixItems": [{ "type": "number" }, { "type": "number" }, { "type": "number" }],
      "minItems": 3,
      "maxItems": 3
    },
    "domain3": {
      "type": "object",
      "properties": {
        "x": { "$ref": "#/$defs/range2" },
        "y": { "$ref": "#/$defs/range2" },
        "z": { "$ref": "#/$defs/range2" }
      }
    },
    "range2": {
      "type": "array",
      "prefixItems": [{ "type": "number" }, { "type": "number" }],
      "minItems": 2,
      "maxItems": 2
    },
    "pointCloudLayer": {
      "type": "object",
      "required": ["id", "type", "name", "visible", "data", "material"],
      "properties": {
        "type": { "const": "point_cloud" },
        "data": {
          "type": "object",
          "required": ["encoding", "columns"],
          "properties": {
            "encoding": { "const": "json-columns" },
            "columns": {
              "type": "object",
              "required": ["x", "y", "z", "color", "size", "alpha"]
            }
          }
        }
      }
    },
    "surfaceGridLayer": {
      "type": "object",
      "required": ["id", "type", "name", "visible", "data", "material"],
      "properties": {
        "type": { "const": "surface_grid" },
        "data": {
          "type": "object",
          "required": ["kind", "encoding", "x", "y", "z", "shape", "order"],
          "properties": {
            "kind": { "const": "grid2d" },
            "encoding": { "const": "json-grid" },
            "order": { "const": "row-major" },
            "alpha": {
              "anyOf": [
                { "type": "array", "items": { "type": "number" } },
                { "type": "null" }
              ]
            },
            "mask": {
              "anyOf": [
                { "type": "array", "items": { "type": "boolean" } },
                { "type": "null" }
              ]
            },
            "shape": {
              "type": "array",
              "prefixItems": [{ "type": "integer" }, { "type": "integer" }],
              "minItems": 2,
              "maxItems": 2
            }
          }
        }
      }
    },
    "absAnnotationLayer": {
      "type": "object",
      "required": ["id", "type", "name", "visible", "space", "data", "route", "label", "style"],
      "properties": {
        "type": { "const": "abs_annotation" },
        "space": {
          "type": "object",
          "required": ["type", "units"],
          "properties": {
            "type": { "const": "anchored_billboard" },
            "units": { "const": "px" },
            "depthMode": { "const": "anchor-depth" }
          }
        },
        "occlusion": {
          "type": "object",
          "properties": {
            "anchor": { "enum": ["depth-test", "none"] },
            "leader": { "enum": ["depth-test", "none"] },
            "label": { "enum": ["depth-test", "none"] }
          }
        },
        "visibility": {
          "type": "object",
          "properties": {
            "hideWhenAnchorOutsideFrustum": { "type": "boolean" },
            "hideLeaderWhenAnchorOutsideFrustum": { "type": "boolean" },
            "hideLabelWhenAnchorOutsideFrustum": { "type": "boolean" }
          }
        },
        "data": {
          "type": "object",
          "required": ["encoding", "anchors"],
          "properties": {
            "encoding": { "const": "json-abs" },
            "anchors": {
              "type": "array",
              "items": {
                "type": "object",
                "required": ["id", "position", "route", "label"],
                "properties": {
                  "id": { "type": "string" },
                  "position": { "$ref": "#/$defs/vec3" },
                  "route": { "type": "array" },
                  "label": { "type": "object" }
                }
              }
            }
          }
        },
        "route": { "type": "array" },
        "label": { "type": "object" },
        "style": {
          "type": "object",
          "properties": {
            "point": { "type": "object" },
            "line": {
              "type": "object",
              "properties": {
                "widthUnit": { "const": "px" },
                "geometry": { "const": "screen-ribbon" }
              }
            },
            "text": { "type": "object" }
          }
        }
      }
    }
  }
}
